r0b0/__init__.py
r0b0/config.py
r0b0_io-0.0.0.dist-info/LICENSE.txt
r0b0_io-0.0.0.dist-info/METADATA
r0b0_io-0.0.0.dist-info/WHEEL
r0b0_io-0.0.0.dist-info/top_level.txt
r0b0_io-0.0.0.dist-info/RECORD
