Metadata-Version: 2.1
Name: r0b0-io
Version: 0.0.0
Summary: Library for connecting hardware and software, like aconnect for anything.
Author-email: Michael Suguitan <m.jp.sgtn@icloud.com>
License: MIT License
Project-URL: Repository, https://github.com/msgtn/r0b0.git
Requires-Python: ~=3.10
License-File: LICENSE.txt
Requires-Dist: aiohttp ==3.9.0
Requires-Dist: aioice ==0.9.0
Requires-Dist: aiosignal ==1.3.1
Requires-Dist: annotated-types ==0.5.0
Requires-Dist: anyio ==3.7.1
Requires-Dist: async-timeout ==4.0.2
Requires-Dist: attrs ==23.1.0
Requires-Dist: av ==10.0.0
Requires-Dist: bidict ==0.22.1
Requires-Dist: bottle ==0.12.25
Requires-Dist: certifi ==2023.7.22
Requires-Dist: cffi ==1.15.1
Requires-Dist: charset-normalizer ==2.1.1
Requires-Dist: click ==8.1.6
Requires-Dist: colorzero ==2.0
Requires-Dist: crc32c ==2.3.post0
Requires-Dist: cryptography ==41.0.6
Requires-Dist: dnspython ==2.2.1
Requires-Dist: eventlet ==0.33.2
Requires-Dist: exceptiongroup ==1.1.2
Requires-Dist: fire ==0.5.0
Requires-Dist: Flask ==2.2.5
Requires-Dist: Flask-Cors ==3.0.10
Requires-Dist: Flask-SocketIO ==5.3.2
Requires-Dist: frozenlist ==1.4.0
Requires-Dist: google-crc32c ==1.5.0
Requires-Dist: gpiozero ==1.6.2
Requires-Dist: greenlet ==2.0.2
Requires-Dist: h11 ==0.14.0
Requires-Dist: httpcore ==0.17.3
Requires-Dist: httpx ==0.24.1
Requires-Dist: idna ==3.4
Requires-Dist: ifaddr ==0.2.0
Requires-Dist: ikpy ==3.0.1
Requires-Dist: itsdangerous ==2.1.2
Requires-Dist: Jinja2 ==3.1.2
Requires-Dist: markdown-it-py ==3.0.0
Requires-Dist: MarkupSafe ==2.1.3
Requires-Dist: mdurl ==0.1.2
Requires-Dist: mpmath ==1.3.0
Requires-Dist: multidict ==6.0.4
Requires-Dist: numpy ==1.24.0
Requires-Dist: opencv-contrib-python ==4.8.0.74
Requires-Dist: opencv-python ==4.8.0.74
Requires-Dist: orjson ==3.9.2
Requires-Dist: pycparser ==2.21
Requires-Dist: pydantic ==2.0.3
Requires-Dist: pydantic-core ==2.3.0
Requires-Dist: pyee ==11.0.0
Requires-Dist: pygame ==2.4.0
Requires-Dist: Pygments ==2.15.1
Requires-Dist: pylibsrtp ==0.8.0
Requires-Dist: pyOpenSSL ==23.2.0
Requires-Dist: pyserial ==3.5
Requires-Dist: python-dateutil ==2.8.2
Requires-Dist: python-dotenv ==1.0.0
Requires-Dist: python-engineio ==4.3.4
Requires-Dist: python-socketio ==5.8.0
Requires-Dist: PyYAML ==6.0.1
Requires-Dist: requests ==2.31.0
Requires-Dist: rich ==13.4.2
Requires-Dist: scipy ==1.11.1
Requires-Dist: six ==1.16.0
Requires-Dist: sniffio ==1.3.0
Requires-Dist: sympy ==1.12
Requires-Dist: termcolor ==2.3.0
Requires-Dist: tornado ==6.3.3
Requires-Dist: typing-extensions ==4.7.1
Requires-Dist: urllib3 ==1.26.18
Requires-Dist: websocket-client ==1.6.1
Requires-Dist: Werkzeug ==2.3.8
Requires-Dist: wget ==3.2
Requires-Dist: yarl ==1.9.2
Provides-Extra: robot
